agr_curation_api/__init__.py
agr_curation_api/api_methods.py
agr_curation_api/client.py
agr_curation_api/db_methods.py
agr_curation_api/exceptions.py
agr_curation_api/graphql_methods.py
agr_curation_api/graphql_queries.py
agr_curation_api/models.py
agr_curation_api/nested_models.py
agr_curation_api/py.typed
agr_curation_api_client-0.8.0.dist-info/licenses/LICENSE
agr_curation_api_client-0.8.0.dist-info/METADATA
agr_curation_api_client-0.8.0.dist-info/WHEEL
agr_curation_api_client-0.8.0.dist-info/top_level.txt
agr_curation_api_client-0.8.0.dist-info/RECORD
