Metadata-Version: 2.4
Name: agr-curation-api-client
Version: 0.8.0
Summary: Unified Python client for Alliance of Genome Resources (AGR) curation APIs
Author-email: Alliance of Genome Resources <valearna@caltech.edu>
Maintainer-email: Alliance Blue Team <valearna@caltech.edu>
License: MIT
Project-URL: Homepage, https://github.com/alliance-genome/agr_curation_api_client
Project-URL: Bug Reports, https://github.com/alliance-genome/agr_curation_api_client/issues
Project-URL: Source, https://github.com/alliance-genome/agr_curation_api_client
Project-URL: Documentation, https://github.com/alliance-genome/agr_curation_api_client#readme
Keywords: agr,alliance,genome,curation,api,client
Classifier: Development Status :: 3 - Alpha
Classifier: Intended Audience :: Developers
Classifier: Intended Audience :: Science/Research
Classifier: License :: OSI Approved :: MIT License
Classifier: Programming Language :: Python :: 3
Classifier: Programming Language :: Python :: 3.8
Classifier: Programming Language :: Python :: 3.9
Classifier: Programming Language :: Python :: 3.10
Classifier: Programming Language :: Python :: 3.11
Classifier: Programming Language :: Python :: 3.12
Classifier: Topic :: Scientific/Engineering :: Bio-Informatics
Requires-Python: >=3.8
License-File: LICENSE
Requires-Dist: requests>=2.28.0
Requires-Dist: pydantic>=2.0.0
Requires-Dist: tenacity>=8.0.0
Requires-Dist: python-dateutil>=2.8.0
Requires-Dist: fastapi_okta>=1.3.0
Requires-Dist: sqlalchemy>=2.0.0
Requires-Dist: psycopg2-binary>=2.9.0
Requires-Dist: linkml>=1.7.0
Requires-Dist: linkml-runtime>=1.7.0
Requires-Dist: pyyaml>=6.0
Provides-Extra: dev
Requires-Dist: pytest>=7.0.0; extra == "dev"
Requires-Dist: pytest-cov>=4.0.0; extra == "dev"
Requires-Dist: pytest-asyncio>=0.21.0; extra == "dev"
Requires-Dist: black>=23.0.0; extra == "dev"
Requires-Dist: flake8>=6.0.0; extra == "dev"
Requires-Dist: mypy>=1.0.0; extra == "dev"
Requires-Dist: types-requests; extra == "dev"
Requires-Dist: types-python-dateutil; extra == "dev"
Dynamic: license-file
